iridi/__init__.py
iridi/iridi.py
iridi/presets.py
iridi-1.3.0.dist-info/LICENSE
iridi-1.3.0.dist-info/METADATA
iridi-1.3.0.dist-info/WHEEL
iridi-1.3.0.dist-info/top_level.txt
iridi-1.3.0.dist-info/RECORD
