Metadata-Version: 2.1
Name: iridi
Version: 1.3.0
Summary: Beautify your command line interfaces
Home-page: https://github.com/cnrad/iridi
Author: Conrad Crawford
Author-email: hello@cnrad.dev
License: GNU GPL 3.0
Platform: UNKNOWN
Classifier: Programming Language :: Python :: 3.9
Classifier: Programming Language :: Python :: 3.8
Classifier: Programming Language :: Python :: 3.7
Classifier: Programming Language :: Python :: 3.6
Classifier: Programming Language :: Python :: 3.5
Requires-Python: >=3.6
License-File: LICENSE
